Metadata-Version: 1.1
Name: django-pycdi
Version: 0.1.0
Summary: DJango with Code Dependency Injection using PyCDI
Home-page: https://github.com/ettoreleandrotognoli/django-pycdi
Author: Éttore Leandro Tognoli
Author-email: ettore.leandro.tognoli@gmail.com
License: BSD
Download-URL: https://github.com/ettoreleandrotognoli/django-pycdi/tree/0.1.0/
Keywords: django,pycdi,cdi,di,code dependency injection,dependency injection
Platform: UNKNOWN
Classifier: Operating System :: OS Independent
Classifier: Programming Language :: Python
Classifier: Programming Language :: Python :: 2
Classifier: Programming Language :: Python :: 3
Classifier: Development Status :: 2 - Pre-Alpha
Classifier: Framework :: Django
Classifier: License :: OSI Approved :: BSD License
